[
    {
        "name": "https://www.glia.com",
        "logo": "https://cdn.prod.website-files.com/680f1550811d9719bdbcf21b/6835fd1ea895df4327eae39d_favicon%20(4).png",
        "internal_link": [
            "https://www.glia.com/security-bounty"
        ],
        "email": [
            "bugs@glia.com",
            "privacy@glia.com",
            "bounty-hunters@glia.atlassian.net"
        ],
        "matched": [
            "We offer reward",
            "eligible for a reward"
        ],
        "last_updated": "2025-11-29"
    }
]